frameworkfusion/__init__.py
frameworkfusion/fusion.py
frameworkfusion-0.1.0.dist-info/METADATA
frameworkfusion-0.1.0.dist-info/WHEEL
frameworkfusion-0.1.0.dist-info/entry_points.txt
frameworkfusion-0.1.0.dist-info/RECORD
